labeling_escaper/__init__.py
labeling_escaper/escaper.cp310-win_amd64.pyd
labeling_escaper/escaper.cp36-win_amd64.pyd
labeling_escaper/escaper.cp37-win_amd64.pyd
labeling_escaper/escaper.cp38-win_amd64.pyd
labeling_escaper/escaper.cp39-win_amd64.pyd
labeling_escaper-1.0.4.dist-info/METADATA
labeling_escaper-1.0.4.dist-info/WHEEL
labeling_escaper-1.0.4.dist-info/top_level.txt
labeling_escaper-1.0.4.dist-info/RECORD
