Metadata-Version: 2.1
Name: labeling-escaper
Version: 1.0.4
Summary: painting tools
Home-page: 
Download-URL: 
Author: sike6054
Author-email: sike6054@gmail.com
License: UNKNOWN
Platform: UNKNOWN
Classifier: Programming Language :: Python :: 3.6
Classifier: Programming Language :: Python :: 3.7
Classifier: Programming Language :: Python :: 3.8
Classifier: Programming Language :: Python :: 3.9
Classifier: Programming Language :: Python :: 3.10
Classifier: License :: OSI Approved :: MIT License
Classifier: Operating System :: OS Independent
Requires-Python: >=3.6, <=3.10
Requires-Dist: PyQt5
Requires-Dist: opencv-python
Requires-Dist: qimage2ndarray
Requires-Dist: PyYAML
Requires-Dist: pillow
